ws_sheets_server/__init__.py
ws_sheets_server/client_aio.py
ws_sheets_server/daemon.py
ws_sheets_server/install.py
ws_sheets_server/packet.py
ws_sheets_server/server.py
ws_sheets_server/server_aio.py
ws_sheets_server/shell.py
ws_sheets_server/ws_sheets_server.service
ws_sheets_server/client/__init__.py
ws_sheets_server/sockets/__init__.py
ws_sheets_server/tests/__init__.py
ws_sheets_server/tests/check_stored.py
ws_sheets_server/tests/client.py
ws_sheets_server/tests/concurrency.py
ws_sheets_server/tests/inherited.py
ws_sheets_server/tests/socket_client.py
ws_sheets_server/tests/socket_server.py
ws_sheets_server/tests/conf/simple.py
ws_sheets_server/tests/conf/simple_console.py
ws_sheets_server-0.4.data/scripts/ws_sheets_server
ws_sheets_server-0.4.dist-info/DESCRIPTION.rst
ws_sheets_server-0.4.dist-info/METADATA
ws_sheets_server-0.4.dist-info/RECORD
ws_sheets_server-0.4.dist-info/WHEEL
ws_sheets_server-0.4.dist-info/metadata.json
ws_sheets_server-0.4.dist-info/top_level.txt
