Metadata-Version: 2.0
Name: ws-sheets-server
Version: 0.4
Summary: server for ws_sheets
Home-page: http://github.com/chuck1/ws_sheets_server
Author: Charles Rymal
Author-email: charlesrymal@gmail.com
License: MIT
Platform: UNKNOWN
